kapitan/__init__.py
kapitan/__main__.py
kapitan/cached.py
kapitan/cli.py
kapitan/defaults.py
kapitan/dependency_manager/__init__.py
kapitan/dependency_manager/base.py
kapitan/errors.py
kapitan/helm_cli.py
kapitan/initialiser.py
kapitan/inputs/__init__.py
kapitan/inputs/base.py
kapitan/inputs/copy.py
kapitan/inputs/cuelang.py
kapitan/inputs/external.py
kapitan/inputs/helm.py
kapitan/inputs/jinja2.py
kapitan/inputs/jsonnet.py
kapitan/inputs/kadet.py
kapitan/inputs/kustomize.py
kapitan/inputs/remove.py
kapitan/inventory/__init__.py
kapitan/inventory/backends/omegaconf/__init__.py
kapitan/inventory/backends/omegaconf/migrate.py
kapitan/inventory/backends/omegaconf/resolvers.py
kapitan/inventory/backends/reclass/__init__.py
kapitan/inventory/backends/reclass_rs/__init__.py
kapitan/inventory/inventory.py
kapitan/inventory/model/__init__.py
kapitan/inventory/model/dependencies.py
kapitan/inventory/model/input_types.py
kapitan/inventory/model/references.py
kapitan/jinja2_filters.py
kapitan/lib/kapitan.libjsonnet
kapitan/lint.py
kapitan/refs/__init__.py
kapitan/refs/base.py
kapitan/refs/base64.py
kapitan/refs/cmd_parser.py
kapitan/refs/env.py
kapitan/refs/functions.py
kapitan/refs/secrets/__init__.py
kapitan/refs/secrets/awskms.py
kapitan/refs/secrets/azkms.py
kapitan/refs/secrets/gkms.py
kapitan/refs/secrets/gpg.py
kapitan/refs/secrets/vaultkv.py
kapitan/refs/secrets/vaulttransit.py
kapitan/refs/vault_resources.py
kapitan/resources.py
kapitan/targets.py
kapitan/utils.py
kapitan/version.py
kapitan-0.34.7.dist-info/AUTHORS
kapitan-0.34.7.dist-info/LICENSE
kapitan-0.34.7.dist-info/METADATA
kapitan-0.34.7.dist-info/WHEEL
kapitan-0.34.7.dist-info/entry_points.txt
kapitan-0.34.7.dist-info/RECORD
