Metadata-Version: 2.1
Name: kapitan
Version: 0.34.7
Summary: Generic templated configuration management for Kubernetes, Terraform and other things
Home-page: https://github.com/kapicorp/kapitan
License: Apache-2.0
Keywords: jsonnet,kubernetes,reclass,jinja
Author: Ricardo Amaro
Author-email: ramaro@kapicorp.com
Requires-Python: >=3.10,<3.13
Classifier: Development Status :: 4 - Beta
Classifier: Intended Audience :: Developers
Classifier: License :: OSI Approved :: Apache Software License
Classifier: Programming Language :: Python :: 3
Classifier: Programming Language :: Python :: 3.10
Classifier: Programming Language :: Python :: 3.11
Classifier: Programming Language :: Python :: 3.12
Classifier: Topic :: Software Development :: Build Tools
Provides-Extra: gojsonnet
Provides-Extra: omegaconf
Provides-Extra: reclass-rs
Requires-Dist: addict (>=2.4.0,<3.0.0)
Requires-Dist: azure-identity (>=1.12.0,<2.0.0)
Requires-Dist: azure-keyvault-keys (>=4.7.0,<5.0.0)
Requires-Dist: boto3 (>=1.18.17,<2.0.0)
Requires-Dist: certifi
Requires-Dist: copier (>=9.3.1,<10.0.0)
Requires-Dist: cryptography (>=3.4.7,<44.0.0)
Requires-Dist: filetype (>=1.2.0,<2.0.0)
Requires-Dist: gitdb (>=4.0.10,<5.0.0)
Requires-Dist: gitpython (>=3.1.30,<4.0.0)
Requires-Dist: gojsonnet (>=0.21.0,<0.22.0) ; extra == "gojsonnet"
Requires-Dist: google-api-python-client (>=2.15.0,<3.0.0)
Requires-Dist: hvac (==2.3.0)
Requires-Dist: jinja2 (>=3.0.1,<4.0.0)
Requires-Dist: jsonnet (>=0.21.0,<0.22.0)
Requires-Dist: jsonpath-ng (>=1.7.0,<2.0.0)
Requires-Dist: jsonschema (>=4.17.3,<5.0.0)
Requires-Dist: kadet (>=0.3.0,<0.4.0)
Requires-Dist: kapicorp-reclass (>=2.0.0)
Requires-Dist: omegaconf (>=2.4.0.dev3,<3.0.0) ; extra == "omegaconf"
Requires-Dist: packaging (>=23,<26)
Requires-Dist: pydantic (>=2.8.2,<3.0.0)
Requires-Dist: pydantic-settings (>=2.4.0,<3.0.0)
Requires-Dist: python-box (>=7.2.0,<8.0.0)
Requires-Dist: python-gnupg (>=0.4.7,<0.6.0)
Requires-Dist: pyyaml (>=6.0,<7.0)
Requires-Dist: reclass-rs (>=0.8.0,<0.9.0) ; extra == "reclass-rs"
Requires-Dist: regex (>=2024.5.10,<2025.0.0)
Requires-Dist: requests (>=2.28.2,<3.0.0)
Requires-Dist: six (>=1.16.0,<2.0.0)
Requires-Dist: strenum (>=0.4.15,<0.5.0) ; python_version >= "3.10" and python_version < "4.0"
Requires-Dist: toml (>=0.10.2,<0.11.0)
Requires-Dist: typing-extensions (>=4.0.0,<5.0.0)
Requires-Dist: yamllint (>=1.29.0,<2.0.0)
Project-URL: Documentation, https://kapitan.dev/
Project-URL: Repository, https://github.com/kapicorp/kapitan
